hyperdoc/__init__.py
hyperdoc/__main__.py
hyperdoc/pyrustic_data/backstage/data/build_report.json
hyperdoc/pyrustic_data/backstage/hooking/build.json
hyperdoc/pyrustic_data/backstage/hooking/init.json
hyperdoc/pyrustic_data/backstage/hooking/release.json
tests/__init__.py
tests/__main__.py
hyperdoc-0.0.1.dist-info/LICENSE
hyperdoc-0.0.1.dist-info/METADATA
hyperdoc-0.0.1.dist-info/WHEEL
hyperdoc-0.0.1.dist-info/entry_points.txt
hyperdoc-0.0.1.dist-info/top_level.txt
hyperdoc-0.0.1.dist-info/RECORD
